[
    {
        "name": "room_template",
        "default_looktext": ["look_text template"]
    },
    {
        "name": "driveway",
        "default_looktext": [
            "The gravel crunches under your feet as you cross the driveway.",
            "Looking back, you can barely make out the road in the distance.",
            "A pile of newspapers lies near the porch.",
            "You're not sure why they kept delivering for so long if no one",
            "was reading them, but it looks like they stopped about a year ago."       
        ],
        "fogofwar":["Diveway Revealed"]
    },
    {
        "name": "porch",
        "default_looktext": ["You are on the porch"],
        "fogofwar":["Porch Revealed"]
    }
]